{"assets":{"95E8E09BE69C930DDFDF98D31EABC1B0":{"type":"texture","index":1,"url":{"native":"assets\/A2092AE3-9354-497E-9694-313DA7E75462.pdf"},"width":1920,"height":1080},"063A7EC07023F473CE33D05001FC2C30":{"type":"texture","index":0,"url":{"native":"assets\/A2092AE3-9354-497E-9694-313DA7E75462.pdf"},"width":1920,"height":1080}},"events":[{"effects":[{"beginTime":0,"baseLayer":{"animations":[],"initialState":{"affineTransform":[1,0,0,1,0,0],"masksToBounds":false,"rotation":0,"scale":1,"position":{"pointX":960,"pointY":540},"width":1920,"sublayerTransform":[1,0,0,0,0,1,0,0,0,0,1,0,0,0,0,1],"contentsRect":{"y":0,"x":0,"width":1,"height":1},"opacity":1,"edgeAntialiasingMask":251658240,"height":1080,"hidden":false,"anchorPoint":{"pointX":0.5,"pointY":0.5}},"objectID":"0","layers":[{"animations":[],"initialState":{"affineTransform":[1,0,0,1,0,0],"masksToBounds":false,"rotation":0,"scale":1,"position":{"pointX":960,"pointY":540},"width":1920,"sublayerTransform":[1,0,0,0,0,1,0,0,0,0,1,-0.00035007912466775983,0,0,0,1],"contentsRect":{"y":0,"x":0,"width":1,"height":1},"opacity":1,"edgeAntialiasingMask":251658240,"height":1080,"hidden":false,"anchorPoint":{"pointX":0.5,"pointY":0.5}},"layers":[{"animations":[],"layers":[],"texturedRectangle":{"isBackgroundTexture":false,"singleTextureOpacity":1,"textureType":0,"textBaseline":0,"textXHeight":0,"isVerticalText":false},"initialState":{"affineTransform":[1,0,0,1,0,0],"masksToBounds":false,"rotation":0,"scale":1,"position":{"pointX":960,"pointY":540},"width":1920,"sublayerTransform":[1,0,0,0,0,1,0,0,0,0,1,0,0,0,0,1],"contentsRect":{"y":0,"x":0,"width":1,"height":1},"opacity":1,"edgeAntialiasingMask":0,"height":1080,"hidden":false,"anchorPoint":{"pointX":0.5,"pointY":0.5}},"texture":"95E8E09BE69C930DDFDF98D31EABC1B0"},{"animations":[{"additive":false,"timeOffset":0,"beginTime":0,"from":{"scalar":false},"repeatCount":0,"fillMode":"both","duration":0.001,"autoreverses":false,"property":"hidden","to":{"scalar":true},"removedOnCompletion":false}],"layers":[],"texturedRectangle":{"isBackgroundTexture":false,"singleTextureOpacity":1,"textureType":0,"textBaseline":0,"textXHeight":0,"isVerticalText":false},"initialState":{"affineTransform":[1,0,0,1,0,0],"masksToBounds":false,"rotation":0,"scale":1,"position":{"pointX":960,"pointY":540},"width":1920,"sublayerTransform":[1,0,0,0,0,1,0,0,0,0,1,0,0,0,0,1],"contentsRect":{"y":0,"x":0,"width":1,"height":1},"opacity":1,"edgeAntialiasingMask":0,"height":1080,"hidden":false,"anchorPoint":{"pointX":0.5,"pointY":0.5}},"texture":"063A7EC07023F473CE33D05001FC2C30"}]}]},"effects":[],"duration":0.001,"type":"transition","attributes":{"direction":0},"name":"none","objectID":"0"}],"automaticPlay":false,"hyperlinks":[],"accessibility":[{"text":"훈련","targetRectangle":{"y":671.00098643411991,"x":378.42981745610757,"width":103.7109375,"height":71}},{"text":"딥러닝","targetRectangle":{"y":106.24950076808506,"x":1385.0037786510281,"width":155.56640625,"height":71}},{"text":"인공 신경망","targetRectangle":{"y":671.0009864287573,"x":1326.2342485836477,"width":273.10546875,"height":71}},{"text":"분석","targetRectangle":{"y":671.00098644075581,"x":213.02226278914588,"width":103.7109375,"height":71}},{"text":"예측","targetRectangle":{"y":671.00098639667408,"x":543.83737216223312,"width":103.7109375,"height":71}},{"text":"머신러닝","targetRectangle":{"y":106.24950071713027,"x":326.57435469913594,"width":207.421875,"height":71}},{"text":"전처리","targetRectangle":{"y":970.79123889688958,"x":558.9268351378546,"width":103.7109375,"height":48}},{"text":"학습 데이터","targetRectangle":{"y":866.63616531009018,"x":213.02226278449473,"width":182.5,"height":48}},{"text":"과대적합","targetRectangle":{"y":371.14910421717491,"x":515.53629844468321,"width":138.28125,"height":48}},{"text":"머신러닝","targetRectangle":{"y":237.55069466447731,"x":1672.116815343292,"width":138.28125,"height":48}},{"text":"규칙","targetRectangle":{"y":582.54076262852254,"x":79.065983857596621,"width":69.140625,"height":48}},{"text":"자체적","targetRectangle":{"y":488.20677534130868,"x":1602.2667963457247,"width":103.7109375,"height":48}},{"text":"자동화","targetRectangle":{"y":261.90456728835693,"x":662.03728386516866,"width":103.7109375,"height":48}},{"text":"뉴런","targetRectangle":{"y":204.46918374003747,"x":1178.4388829377253,"width":69.140625,"height":48}},{"text":"결정","targetRectangle":{"y":582.54076281622406,"x":1153.2517752490996,"width":69.140625,"height":48}},{"text":"과소적합","targetRectangle":{"y":776.1192707060344,"x":677.25685501857038,"width":138.28125,"height":48}},{"text":"훈련 데이터","targetRectangle":{"y":315.52284923486087,"x":182.53429567837583,"width":182.5,"height":48}},{"text":"신경망","targetRectangle":{"y":899.35981923614315,"x":1231.8294005498224,"width":103.7109375,"height":48}}],"baseLayer":{"animations":[],"initialState":{"affineTransform":[1,0,0,1,0,0],"masksToBounds":false,"rotation":0,"scale":1,"position":{"pointX":960,"pointY":540},"width":1920,"sublayerTransform":[1,0,0,0,0,1,0,0,0,0,1,0,0,0,0,1],"contentsRect":{"y":0,"x":0,"width":1,"height":1},"opacity":1,"edgeAntialiasingMask":251658240,"height":1080,"hidden":false,"anchorPoint":{"pointX":0.5,"pointY":0.5}},"objectID":"0","layers":[{"animations":[],"initialState":{"affineTransform":[1,0,0,1,0,0],"masksToBounds":false,"rotation":0,"scale":1,"position":{"pointX":960,"pointY":540},"width":1920,"sublayerTransform":[1,0,0,0,0,1,0,0,0,0,1,-0.00035007912466775983,0,0,0,1],"contentsRect":{"y":0,"x":0,"width":1,"height":1},"opacity":1,"edgeAntialiasingMask":251658240,"height":1080,"hidden":false,"anchorPoint":{"pointX":0.5,"pointY":0.5}},"layers":[{"animations":[],"layers":[],"texturedRectangle":{"isBackgroundTexture":false,"singleTextureOpacity":1,"textureType":0,"textBaseline":0,"textXHeight":0,"isVerticalText":false},"initialState":{"affineTransform":[1,0,0,1,0,0],"masksToBounds":false,"rotation":0,"scale":1,"position":{"pointX":960,"pointY":540},"width":1920,"sublayerTransform":[1,0,0,0,0,1,0,0,0,0,1,0,0,0,0,1],"contentsRect":{"y":0,"x":0,"width":1,"height":1},"opacity":1,"edgeAntialiasingMask":0,"height":1080,"hidden":false,"anchorPoint":{"pointX":0.5,"pointY":0.5}},"texture":"063A7EC07023F473CE33D05001FC2C30"}]}]}}]}